{
  "url": "https://science.house.gov/press-releases?page=90",
  "title": "House Committee on Science Space & Tech",
  "description": null,
  "text": "Failure of Leadership at Chemical Safety Board Puts Public at Risk\nNew Technologies Could Prevent Thousands of Automobile Crashes Annually\nSmith Statement on House Passage of Bill to Mitigate Harmful Algal Blooms\nSmith: New EPA Power Plant Regs ‘All Pain, No Gain’",
  "authors": [],
  "date_publish": "2026-06-19 00:00:00",
  "language": "en",
  "source_domain": "science.house.gov",
  "crawled_at": "2026-03-01T14:24:07.635077",
  "parent_url": "https://science.house.gov/press-releases",
  "article_number": 46,
  "website_id": 31
}