{
  "url": "https://www6.slac.stanford.edu/topics/sensors-integrated-circuits-electronics",
  "title": "Topic: Sensors, integrated circuits & electronics",
  "description": "See content related to sensors, integrated circuits & electronics here below.",
  "text": "SLAC topics\nSensors, integrated circuits & electronics RSS feed\nSee content related to sensors, integrated circuits & electronics here below.\nFilter by Type\nFeature\nSLAC experts discuss how microelectronics impacts our lives and where the future lies in this Q&A.\nNews Release\nSLAC and Stanford partner with Argonne National Laboratory and others toward a quantum-interconnected world.\nFeature\nThe microelectronics that power daily life and speed discoveries in science and technology are the focus of a bold new vision to make them...\nFeature\nResearchers across the lab are developing AI tools to harness data and particle beams in real time and make molecular movies, speeding up the...\nFeature\nDigital design engineer Abhilasha Dave’s passion for connecting machine learning and hardware is helping SLAC solve big data challenges.\nFeature\nDavid Cesar, Julia Gonski and W.L. Kimmy Wu will each receive $2.75 million issued over five years for their research in X-ray and ultrafast...\nVideo\nLearn about the 10-year Legacy Survey of Space and Time (LSST), the SLAC-built LSST Camera and NSF-DOE Vera C. Rubin Observatory in this video.\nVideo\nFeature\nThe ePix series of detectors is designed to keep pace with ever more demanding experiments at SLAC and elsewhere.\nFeature\nThe ePix10k detector is ready to advance science at SLAC’s Linac Coherent Light Source X-ray laser and at facilities around the world.\nFeature\nAfter meeting at a party, a Stanford psychologist and SLAC particle physicists have collaborated on a new kind of EEG device that can stimulate...\nFeature\nMonika Schleier-Smith and Kent Irwin explain how their projects in quantum information science could help us better understand black holes and dark matter.\nFeature\nThe newly launched Quantum Fundamentals, ARchitecture and Machines initiative will build upon existing strengths in theoretical and experimental quantum science and engineering at Stanford...\nSLAC experts discuss how microelectronics impacts our lives and where the future lies in this Q&A.\nSLAC and Stanford partner with Argonne National Laboratory and others toward a quantum-interconnected world.\nThe microelectronics that power daily life and speed discoveries in science and technology are the focus of a bold new vision to make them more energy efficient and able to operate in extreme environments.\nResearchers across the lab are developing AI tools to harness data and particle beams in real time and make molecular movies, speeding up the discovery process in the era of big data.\nDigital design engineer Abhilasha Dave’s passion for connecting machine learning and hardware is helping SLAC solve big data challenges.\nDavid Cesar, Julia Gonski and W.L. Kimmy Wu will each receive $2.75 million issued over five years for their research in X-ray and ultrafast science, new physics and primordial gravitational waves.\nLearn about the 10-year Legacy Survey of Space and Time (LSST), the SLAC-built LSST Camera and NSF-DOE Vera C. Rubin Observatory in this video.\nVideo\nThe ePix series of detectors is designed to keep pace with ever more demanding experiments at SLAC and elsewhere.\nThe ePix10k detector is ready to advance science at SLAC’s Linac Coherent Light Source X-ray laser and at facilities around the world.\nFeature · VIA Stanford News\nParticle physicists lend a hand to advance neuroscience\nAfter meeting at a party, a Stanford psychologist and SLAC particle physicists have collaborated on a new kind of EEG device that can stimulate the brain and read out the effects.\nMonika Schleier-Smith and Kent Irwin explain how their projects in quantum information science could help us better understand black holes and dark matter.\nThe newly launched Quantum Fundamentals, ARchitecture and Machines initiative will build upon existing strengths in theoretical and experimental quantum science and engineering at Stanford and SLAC.",
  "authors": [],
  "date_publish": "None",
  "language": "en",
  "source_domain": "www6.slac.stanford.edu",
  "crawled_at": "2026-03-01T18:46:54.058991",
  "parent_url": "https://www6.slac.stanford.edu/news-and-events",
  "article_number": 74,
  "website_id": 91
}