{
  "url": "https://www.sandia.gov/research/publications/details/a-multivariate-space%e2%80%90time-dynamic-model-for-characterizing-the-atmo-2025-08-12/",
  "title": "A Multivariate Space‐Time Dynamic Model for Characterizing the Atmospheric Impacts Following the Mt. Pinatubo Eruption",
  "description": null,
  "text": "A Multivariate Space‐Time Dynamic Model for Characterizing the Atmospheric Impacts Following the Mt. Pinatubo Eruption\nGarrett, Robert C.; Shand, Lyndsay; Huerta, Jose G.\nThe June 1991 Mt. Pinatubo eruption resulted in a massive increase of sulfate aerosols in the atmosphere, absorbing radiation and leading to global changes in surface and stratospheric temperatures. A volcanic eruption of this magnitude serves as a natural analog for stratospheric aerosol injection, a proposed solar radiation modification method to combat a warming climate. The impacts of such an event are multifaceted and region-specific. Our goal is to characterize the multivariate and dynamic nature of the atmospheric impacts following the Mt. Pinatubo eruption. We developed a multivariate space-time dynamic linear model to understand the full extent of the spatially- and temporally-varying impacts. Specifically, spatial variation is modeled using a flexible set of basis functions for which the basis coefficients are allowed to vary in time through a vector autoregressive (VAR) structure. This novel model is cast in a Dynamic Linear Model (DLM) framework and estimated via a customized MCMC approach. We demonstrate how the model quantifies the relationships between key atmospheric parameters prior to and following the Mt. Pinatubo eruption with reanalysis data from MERRA-2 and highlight when such a model is advantageous over univariate models.",
  "authors": [],
  "date_publish": "2025-08-12 00:00:00",
  "language": "en",
  "source_domain": "www.sandia.gov",
  "crawled_at": "2026-03-01T18:31:56.230446",
  "parent_url": "https://www.sandia.gov/research/publications/search/",
  "article_number": 76,
  "website_id": 80
}