{
  "url": "https://www.sandia.gov/research/area/computing-information-science-and-mathematics/ai/",
  "title": "Artificial Intelligence (AI)",
  "description": "Overview of Sandia's Artificial Intelligence strategic focus areas",
  "text": "Artificial Intelligence at Sandia\nSandia’s AI Strategic Focus Areas\nIntroduction\nSandia delivers essential science and technology to resolve the most challenging national security issues. Science-based, systems-engineering solutions are delivered through ground-breaking work in secure AI, computing co-design, and scientific machine learning.\nSandia is partnering with industry, government, and academia to advance AI capabilities through research, development, and deployment. These collaborations facilitate support of DOE’s AI initiatives, including the transfer and commercialization of award-winning AI technology, and the training of future leaders who must anticipate and tackle problems facing the nation.\nSandia AI News Releases\nFeatured Sandia AI Videos\nCurrent AI, ML, Computing, and Advanced Simulation Openings",
  "authors": [],
  "date_publish": "None",
  "language": "en",
  "source_domain": "www.sandia.gov",
  "crawled_at": "2026-03-01T18:30:05.532004",
  "parent_url": "https://www.sandia.gov/research/rd-100-awards/",
  "article_number": 56,
  "website_id": 81
}