{
  "url": "https://www.ameslab.gov/news/news-releases?page=2#main-content",
  "title": "News Releases",
  "description": null,
  "text": "Ames National Laboratory partners with NETL and other DOE labs to launch a new critical materials research facility\nAmes National Laboratory will partner with eight other DOE National Laboratories to support the Critical Materials Supply Chain Research Facility recently announced by the U.S. Department of Energy’s (DOE) Office of Fossil Energy and Carbon Management. Ames Lab will lead the Critical Materials Refinery Center, one of four Centers to be established in the Facility.\nScientists reveal the first unconventional superconductor that can be found in mineral form in nature\nScientists from Ames National Laboratory have identified the first unconventional superconductor with a chemical composition also found in nature.\nIowa Regional Middle School Science Bowl to be held March 2\nAmes National Laboratory and Iowa State University will host the 21st annual Iowa Regional Middle School Science Bowl. The event will take place Saturday, Mar. 2, 2024, on the Iowa State campus.\nAmes National Laboratory announces search for Chief Operations Officer\nAmes National Laboratory announced today that they will conduct a search for its next Chief Operations Officer, who will assume oversight of the Laboratory’s business, facilities, and operations management.\nScientists shed light on the inner workings of a new class of unconventional superconductors\nA team of scientists from the U.S. Department of Energy’s Ames National Laboratory and SLAC National Accelerator Laboratory has provided new data and analysis on infinite-layer nickelates. This material is a recently discovered class of unconventional superconductors. The results provide new insights into how these superconductors work and how they differ from other superconductors.\nScience Bowl to be held in February\nAmes National Laboratory and Iowa State University will host the 34th annual Iowa Regional High School Science Bowl on Saturday, Feb. 3, 2024. The event will take place on the Iowa State campus.\nTheoretical modeling illuminates a new nonlinear Hall Effect\nAn international team of researchers including a team from the Center for the Advancement of Topological Semimetals (CATS), an Energy Frontier Research Center under the U.S. Department of Energy’s Office of Science led by Ames National Laboratory, experimentally demonstrated a new type of nonlinear Hall effect.\nCMI Hub makes key step to process rare earth metals in United States\nThe Critical Materials Innovation Hub (CMI Hub) worked with industry to take a key step in how to process rare earth metals in the United States. This will help the U.S. supply chain for magnets.",
  "authors": [],
  "date_publish": "None",
  "language": "en",
  "source_domain": "www.ameslab.gov",
  "crawled_at": "2026-03-01T14:36:00.900062",
  "parent_url": "https://www.ameslab.gov/news/news-releases",
  "article_number": 83,
  "website_id": 36
}