{
  "url": "https://www.afacpo.com/mpm/tag/new-version/page/2/",
  "title": "DAF Modernization Process Model",
  "description": null,
  "text": "To enhance the functionality of the Modernization Process Model, the SAF/AQXP Strategic Change Management team added a “Detailed On” section to the process metadata. This feature is available for processes with lower-level details and provides users with an additional way to access associated subprocesses through a clickable link. If you have any questions, comments, or recommendations please reach out to us using our Contact Us page.\nContinue Reading\nThe SAF/AQXP Strategic Change Management team has updated the MPM to version 26.01.13. This version of the model includes three new best practices/lessons learned documents and has had several AMIC processes updated to point to their new PowerApp Playbook when referencing various figures. In addition, the MPM has a new version numbering format which will follow a format of YY.MM.DD so users will always know when the last time the model was updated. If you have have any questions, comments, or suggestions please reach out to us using the the Contact Us page.\nContinue Reading\nThe SAF/AQXP SCM Team has updated the Modernization Process Model (MPM) to version 16.6. This up incorporates recent Department of Defense (DoD) and Department of the Air Force (DAF) policy and regulatory changes impacting acquisition and contracting processes. The release integrates DoDM 5010.12, Acquisition and Management of Contractor-Prepared Data (21 November 2025), along with updated DFARS and DAFFARS guidance affecting Commercial Solutions Openings (CSOs), acquisition planning, and congressional notification requirements. It also updates Urgent Capability Acquisition processes through incorporation of DoDI 5000.81 / DAFI 63-147 (9 December 2025) and adds Space Force–specific descriptions, references, and templates to support urgent operational needs workflows. Additional enhancements include alignment with DoDI 5000.35 (Defense… Read More\nContinue Reading\nThe Modernization Process Model (MPM) has been updated to version 16.5 by the SAF/AQXP SCM Team. This release aligns the model with recent Department of the Air Force (DAF) and Department of Defense (DoD) policies, guidance, and best practices. This update includes the addition of the Cyber Operational Test and Evaluation Guidebook (5 March 2025) and Implementing a Modular Open Systems Approach in DoD Programs (February 2025). It also incorporates updated versions of the Human Systems Integration Guidebook (May 2022, Change 1 June 2024) and the Technology Readiness Assessment Guidance (February 2025). For a full list of all additions and updates made to the MPM, please visit the Document Changes… Read More\nContinue Reading\nPublication Notice – Modernization Process Model (MPM) Version 16.4 The Modernization Process Model (MPM) has been updated to Version 16.4 by the SAF/AQXP SCM Team. This release incorporates several new and updated Department of the Air Force and DoD policy documents to ensure continued alignment with current guidance and best practices. Newly added references include DAFI 38-106, Manpower Programming (16 Sept 2025), DAFI 61-104, Management of Science and Technical Information (STINFO) (25 Aug 2025), DoD Cost Estimating Guide (2 Feb 2022), DoDI 4245.15, Diminishing Manufacturing Sources and Material Shortages Management (4 Nov 2020, Change 2 Sept 2025), DoDI 5000.79, Defense-Wide Sharing and Use of Supplier and Product Performance Information (15… Read More\nContinue Reading",
  "authors": [],
  "date_publish": "2026-01-22 11:24:07",
  "language": "en",
  "source_domain": "www.afacpo.com",
  "crawled_at": "2026-03-01T14:42:00.239060",
  "parent_url": "https://www.afacpo.com/apm/",
  "article_number": 65,
  "website_id": 35
}