{
  "url": "https://www.usni.org/proceedings-magazine/all-issues",
  "title": "All Issues | U.S. Naval Institute",
  "text": "All Issues | U.S. Naval Institute\nThis website uses cookies to improve your browsing experience. By using this site, you agree to our use of cookies.\nView our Privacy Policy.\nCookie Consent plugin for the EU cookie law\nI Accept\nSkip to main content\nCollapse\nDonate\nCart\nJoin or Log In\nSearch\nMain navigation\nAbout Us\nMembership\nBooks & Press\nUSNI News\nProceedings\nNaval History\nArchives\nEvents\nDonate\nCollapse\nDonate\nCart\nJoin or Log In\nSearch\nMain navigation (Sticky)\nAbout Us\nMembership\nBooks & Press\nUSNI News\nProceedings\nNaval History\nArchives\nEvents\nDonate\nSub Menu\nPeriodicals Archive\nNaval History Magazine Archive\nProceedings Archive\nOral Histories\nAbout the Oral History Program\nOrder Oral Histories\nMemoirs\nPhotos\nAbout the Archives\nContact the Archives\nAll Issues\nSub Menu\nPeriodicals Archive\nNaval History Magazine Archive\nProceedings Archive\nOral Histories\nAbout the Oral History Program\nOrder Oral Histories\nMemoirs\nPhotos\nAbout the Archives\nContact the Archives\nYear\n- All -\n2026\n2025\n2024\n2023\n2022\n2021\n2020\n2019\n2018\n2017\n2016\n2015\n2014\n2013\n2012\n2011\n2010\n2009\n2008\n2007\n2006\n2005\n2004\n2003\n2002\n2001\n2000\n1999\n1998\n1997\n1996\n1995\n1994\n1993\n1992\n1991\n1990\n1989\n1988\n1987\n1986\n1985\n1984\n1983\n1982\n1981\n1980\n1979\n1978\n1977\n1976\n1975\n1974\n1973\n1972\n1971\n1970\n1969\n1968\n1967\n1966\n1965\n1964\n1963\n1962\n1961\n1960\n1959\n1958\n1957\n1956\n1955\n1954\n1953\n1952\n1951\n1950\n1949\n1948\n1947\n1946\n1945\n1944\n1943\n1942\n1941\n1940\n1939\n1938\n1937\n1936\n1935\n1934\n1933\n1932\n1931\n1930\n1929\n1928\n1927\n1926\n1925\n1924\n1923\n1922\n1921\n1920\n1919\n1918\n1917\n1916\n1915\n1914\n1913\n1912\n1911\n1910\n1909\n1908\n1907\n1906\n1905\n1904\n1903\n1902\n1901\n1900\n1899\n1898\n1897\n1896\n1895\n1894\n1893\n1892\n1891\n1890\n1889\n1888\n1887\n1886\n1885\n1884\n1883\n1882\n1881\n1880\n1879\n1878\n1877\n1876\n1875\n1874\nMonth\n- All -\nJan\nFeb\nMar\nApr\nMay\nJun\nJul\nAug\nSep\nOct\nNov\nDec\nApply\nProceedings - March 2026 Vol. 152/3/1,477\nProceedings - February 2026 Vol. 152/2/1,476\nProceedings - January 2026 Vol. 152/1/1,475\nProceedings - December 2025 Vol. 151/12/1,474\nProceedings - November 2025 Vol. 151/11/1,473\nProceedings - October 2025 Vol. 151/10/1,472\nProceedings - September 2025 Vol. 151/9/1,471\nProceedings - August 2025 Vol. 151/8/1,470\nProceedings - July 2025 Vol. 151/7/1,469\nProceedings - June 2025 Vol. 151/6/1,468\nProceedings - May 2025 Vol. 151/5/1,467\nProceedings - April 2025 Vol. 151/4/1,466\nPagination\nCurrent page\n1\nPage\n2\nPage\n3\nPage\n4\nPage\n5\nPage\n6\nPage\n7\nPage\n8\nPage\n9\n…\nNext page\n››\nLast page\nLast »\nDigital\nProceedings\ncontent made possible by a gift from CAPT Roger Ekman, USN (Ret.)\nQuicklinks\nFooter menu\nAbout the Naval Institute\nBooks & Press\nNaval History\nUSNI News\nProceedings\nOral Histories\nEvents\nNaval Institute Foundation\nPhotos & Historical Prints\nAdvertise With Us\nNaval Institute Archives\nShop Our Ship's Store\nReceive the Newsletter\nSign up to get updates about new releases and event invitations.\nSign Up Now\nExample Newsletter\nPrivacy Policy\nCopyright © 2026 U.S. Naval Institute\nPrivacy Policy\nTerms of Use\nContact Us\nAdvertise With Us\nFAQ\nContent License\nMedia Inquiries\nFacebook\nTwitter\nLinkedIn\nInstagram",
  "crawled_at": "2026-03-03T13:39:23.248312",
  "parent_url": "https://www.usni.org/magazines/proceedings/current-issue",
  "page_number": 28,
  "website_id": 90,
  "type": "fallback_page"
}