{
  "url": "https://www.onr.navy.mil/freedom-information-act",
  "title": "Freedom of Information Act",
  "description": "The Office of Naval Research (ONR) Privacy Office is responsible for processing Freedom of Information Act, or FOIA, requests.",
  "text": "Notice: As a result of increases in the Health Protection Condition (HPCON) level, our offices are limited to mission-essential personnel only and maximizing the use of telework for other personnel. This means that we are unable to handle requests sent via mail or fax and can only respond to electronic inquiries received via email at onrfoia@navy.mil or submitted to SecureRelease while under elevated HPCON levels.",
  "authors": [],
  "date_publish": "2022-04-21 19:36:55",
  "language": "en",
  "source_domain": "www.onr.navy.mil",
  "crawled_at": "2026-03-01T18:17:54.838805",
  "parent_url": "https://www.onr.navy.mil/media-center/future-force-magazine",
  "article_number": 47,
  "website_id": 78
}