{
  "url": "https://www.onr.navy.mil/organization/departments/code-33/materials-focus-area/organic-photovoltaics",
  "title": "Office of Naval Research",
  "description": "The Organic Photovoltaics program is part of the Office of Naval Research's Mission Capable, Persistent and Survivable Naval Platforms Department.",
  "text": "Organic photovoltaics have the potential to be low cost, rugged, flexible, printed conformably on surfaces, and tunable to absorb in certain spectral windows and to be transparent in others. Record research cells have reached 14 percent power conversion efficiency propelled by the advance of non-fullerene acceptors, however, this is still below the Shockley-Queisser theoretical limit of 33 percent. The various contributions to the losses that limit efficiency are understood, but mitigating these losses is difficult in systems with low order and many interfaces. There is an improved understanding of the charge separation processes at the donor acceptor interface, but more work is needed to fully understand the process and allow design of an optimal junction.\nHalide perovskite and organic solar cells have the potential to be manufactured with low cost processing methods. Applied research is needed to understand how to form desired active layer morphologies in processes that more closely mimic commercial manufacturing methods. Applied research is also needed to study the stability of organic and hybrid solar cells.\nThe basic research program is primarily focused on:\nDeveloping a better understanding of the photovoltaic processes in organic bulk heterojunction solar cells, including absorption, exciton formation and diffusion, charge separation, and charge transport and collection\nImproving overall power conversion efficiency by first understanding the sources of loss and how to mitigate them\nSuch research may necessarily include broad expertise:\nDesign and synthesis of new materials\nMultiscale computation\nDevice fabrication and optimization\nMorphology characterization\nSpectroscopy\nPossibly some insight into the nature of order at the donor/acceptor interface\nIn the long term it is envisioned that the design of donors and acceptors will proactively enhance performance by enabling facile formation of domain structure, along with desired packing within the domains and at domain interfaces.\nApplied research may include hybrid approaches and is targeted toward understanding how to create desired morphologies in processes that mimic those in commercial manufacturing. Applied research may also include stability studies.\nFor detailed application and submission information for this research topic, please refer to our broad agency announcement (BAA) No. N0001425SB001.\nContracts: All white papers and full proposals for contracts must be submitted through the ONR Submission Portal; instructions are included in the BAA.\nGrants: All white papers for grants must be submitted through the ONR Submission Portal, and full proposals for grants must be submitted through grants.gov; instructions are included in the BAA.",
  "authors": [],
  "date_publish": "2022-03-18 21:23:50",
  "language": "en",
  "source_domain": "www.onr.navy.mil",
  "crawled_at": "2026-03-01T18:26:17.884036",
  "parent_url": "https://www.onr.navy.mil/media-center/future-force-magazine",
  "article_number": 91,
  "website_id": 78
}