{
  "url": "https://newscenter.lbl.gov/in-the-news/page/3/",
  "title": "Berkeley Lab News Center",
  "description": null,
  "text": "In the News\nMicrosoft CEO Satya Nadella Just Delivered Bad News to Artificial Intelligence Investors\nResearchers achieve exaflop accuracy to map electron motion inside complex materials\n7,000 Nvidia chips help supercomputer simulate quantum chip in record detail\nGeorge Smoot obituary: Charismatic cosmologist who revealed ripples in the Big Bang’s afterglow\nAI Hype Vs. Hard Value: Why Leaders Must Shift From Buzz To Maturity\nWhat Quantum Computer Makers Will Be Showing at SC25\nPretty much everything you need to know about Manitoba’s new obsession with AI data centres\nShaping the Future of HPC through Architectural Innovation and Industry Collaboration\nData centers are coming to towns but what’s the cost?\nQuantum computing could be the next tech boom — Here’s California’s plan to stay at the center of it\nEpsilon Advanced Materials Anticipates EV Batteries For 1 Million US-Made EVs Per Year … Are They Nuts?\nWhy are Maryland power bills spiking? Is AI to blame?",
  "authors": [],
  "date_publish": "2022-11-19 00:00:00",
  "language": "en",
  "source_domain": "newscenter.lbl.gov",
  "crawled_at": "2026-03-01T14:07:53.768940",
  "parent_url": "https://newscenter.lbl.gov/all-news/",
  "article_number": 8,
  "website_id": 29
}