{
  "url": "https://www.srnl.gov/connect-with-us/",
  "title": "Connect With Us",
  "description": "Connect With Us SRNL Contact Information Media Contacts Journalists with questions about the Savannah River National Laboratory, may contact: Jeff Carterjeffrey.carter@srnl.doe.gov  Technology Transfer For information about working with SRNL in the development and use of new technology, contact: Daren Timmonsdaren.timmons@srnl.doe.gov Protocol Office Questions about business-related events or visits to SRNL should be directed to:  Kelsie TaylorKelsie.Taylor@srnl.doe.gov...",
  "text": "Institutional Biosafety Committee\nThe Institutional Biosafety Committee (IBC) of the Savannah River National Laboratory (SRNL) provides guidance for and oversight of work with potentially biohazardous organisms in order to protect the health and safety of workers, the public, and the environment. Research conducted or sponsored by SRNL will be performed in compliance with federal and state regulations and standards.\nThe IBC must review and approve all research and teaching projects involving hazardous biological materials. At SRNL this research involves working with Recombinant or Synthetic Nucleic Acids.\nMinutes of the IBC’s meetings are available to the public upon request. To request a copy of the minutes, email SRNL_Communications@srnl.doe.gov, subject: IBC minutes.",
  "authors": [],
  "date_publish": "2023-07-07 15:51:33",
  "language": "en",
  "source_domain": "www.srnl.gov",
  "crawled_at": "2026-03-03T13:55:23.460024",
  "parent_url": "https://www.srnl.gov/newsroom/news-releases/",
  "article_number": 57,
  "website_id": 84
}