{
  "url": "https://www.niimbl.org/projects-programs/viral-vectors/",
  "title": "Viral Vectors Program",
  "description": "NIIMBL-Led Program: Viral Vectors aims to develop a shared platform for development, manufacturing, and characterization of AAV-based gene therapy vectors.",
  "text": "One of the most important vector platforms in use in the biopharmaceutical industry today is adeno-associated virus (AAV) vectors. Our Program focuses on advancing the manufacturing process and analytical capabilities for AAV vectors. The advances are critical for broad and rapid expansion of the emerging industry of gene-based therapeutics and ultimately the many patients and families who can benefit from access to these novel therapies.\nNIIMBL is well-positioned to bring together the right resources to accelerate development of core manufacturing process platforms and essential analytical capabilities for viral vector product and process characterization, which can",
  "authors": [],
  "date_publish": "2026-01-03 00:00:00",
  "language": "en",
  "source_domain": "www.niimbl.org",
  "crawled_at": "2026-03-03T13:07:32.665476",
  "parent_url": "https://www.niimbl.org/news/",
  "article_number": 19,
  "website_id": 74
}