{
  "url": "https://www.nasa.gov/no-fear-act/",
  "title": "No FEAR Act",
  "description": "Section 201 of the Notification and Federal Employee Antidiscrimination and Retaliation Act of 2002 (the No FEAR Act) requires Federal agencies to notify all",
  "text": "NASA Equal Employment Opportunity Data Posted Pursuant to the No FEAR Act\nSection 201 of the Notification and Federal Employee Antidiscrimination and Retaliation Act of 2002 (the No FEAR Act) requires Federal agencies to notify all employees, former employees, and applicants for Federal employment of the rights and protections available to them under the Federal antidiscrimination laws and whistleblower protection laws. In addition, Section 301 requires each Federal agency to post summary statistical data pertaining to complaints of employment discrimination filed against it by employees, former employees, and applicants for employment under 29 C.F.R. Part 1614. The specific data to be posted is described in section 301(b) of the Act and 29 CFR 1614.704. The required No FEAR Act Notice and the required summary statistical data for EEO complaints filed against NASA and each NASA Center are available below.\n2026 First Quarter Reports:\nNASA Agency-wide Complaint Activity 1Q\nAmes Research Center Complaint Activity 1Q\nArmstrong Flight Research Center Complaint Activity 1Q\nGlenn Research Center Complaint Activity 1Q\nGoddard Space Flight Center Complaint Activity 1Q\nHeadquarters Complaint Activity 1Q\nJohnson Space Center Complaint Activity 1Q\nKennedy Space Center Complaint Activity 1Q\nLangley Research Center Complaint Activity 1Q\nMarshall Space Flight Center Complaint Activity 1Q\nNASA Shared Services Center Complaint Activity 1Q\nStennis Space Center Complaint Activity 1Q\n2025 Fourth Quarter Reports:\nNASA Agency-wide Complaint Activity 4Q\nAmes Research Center Complaint Activity 4Q\nArmstrong Flight Research Center Complaint Activity 4Q\nGlenn Research Center Complaint Activity 4Q\nGoddard Space Flight Center Complaint Activity 4Q\nHeadquarters Complaint Activity 4Q\nJohnson Space Center Complaint Activity 4Q\nKennedy Space Center Complaint Activity 4Q\nLangley Research Center Complaint Activity 4Q\nMarshall Space Flight Center Complaint Activity 4Q\nNASA Shared Services Center Complaint Activity 4Q\nStennis Space Center Complaint Activity 4Q\nFile a Complaint\nProhibited personnel practices are employment-related activities that are banned in the federal workf​​orce because they violate the merit system through some form of retaliation, improper hiring practices, or failure to adhere to laws, rules, or regulations that directly concern the merit system principles. The Office of Special Counsel (OSC) is authorized to investigate and prosecute claims that occurred in the federal workplace. To learn more, visit the OSC website.\nReference Documents:",
  "authors": [
    "Terri Littrell"
  ],
  "date_publish": "2018-08-10 18:41:47",
  "language": "en",
  "source_domain": "www.nasa.gov",
  "crawled_at": "2026-03-03T12:09:06.943943",
  "parent_url": "https://www.nasa.gov/glenn-news/",
  "article_number": 62,
  "website_id": 64
}