{
  "url": "https://www.sda.mil/space-development-agency-makes-award-to-build-eight-satellites-for-foo-fighter-program/",
  "title": "Space Development Agency Makes Award to Build Eight Satellites for FOO Fighter Program",
  "description": null,
  "text": "Date: April 30, 2024\nWASHINGTON, D.C. – The Space Development Agency (SDA) today announced an award using Other Transaction Authority (OTA) with a total potential value of approximately $414 million to build eight satellites, for launch in first quarter fiscal year 2027, to accelerate fire-control capability for global detection, warning, and precision tracking of advanced missile threats, including hypersonic missile systems.\nThis firm fixed-price agreement was awarded to Millennium Space Systems, Inc. of El Segundo, California to deliver eight satellites as part of the Proliferated Warfighter Space Architecture’s (PWSA) Fire-control On Orbit-support-to-the-war Fighter (FOO Fighter) program. FOO Fighter, or F2, will demonstrate advanced missile defense capability by incorporating fire control-quality sensors into a prototype constellation.\n“The FOO Fighter program will provide an operational demonstration of fire control efforts separate from, but complementary to, our missile warning/missile tracking and missile defense efforts already underway in the tranches,” said Derek Tournear, SDA director. “We look forward to working with Millennium, a new teammate in the expanding marketplace of performers innovating to deliver the PWSA for the warfighter.”\nAbout the Space Development Agency. As part of the U.S. Space Force, SDA is recognized as DOD’s constructive disruptor for space acquisition. SDA will accelerate delivery of needed space-based capabilities to the joint warfighter to support terrestrial missions through development, fielding, and operation of the Proliferated Warfighter Space Architecture. For more information on SDA, contact OSD.SDA.Outreach@mail.mil or visit https://www.sda.mil.\n-END-",
  "authors": [
    "Team"
  ],
  "date_publish": "2024-04-30 16:59:11",
  "language": "en",
  "source_domain": "www.sda.mil",
  "crawled_at": "2026-03-03T13:23:02.441293",
  "parent_url": "https://www.sda.mil/home/news/",
  "article_number": 94,
  "website_id": 82
}